CHANGES.rst
CONTRIBUTORS.rst
DEVELOP.rst
LICENSE.GPL
LICENSE.rst
MANIFEST.in
README.rst
setup.cfg
setup.py
docs/index.rst
src/iaweb/__init__.py
src/iaweb.mosaic.egg-info/PKG-INFO
src/iaweb.mosaic.egg-info/SOURCES.txt
src/iaweb.mosaic.egg-info/dependency_links.txt
src/iaweb.mosaic.egg-info/entry_points.txt
src/iaweb.mosaic.egg-info/namespace_packages.txt
src/iaweb.mosaic.egg-info/not-zip-safe
src/iaweb.mosaic.egg-info/requires.txt
src/iaweb.mosaic.egg-info/top_level.txt
src/iaweb/mosaic/__init__.py
src/iaweb/mosaic/configure.zcml
src/iaweb/mosaic/interfaces.py
src/iaweb/mosaic/permissions.zcml
src/iaweb/mosaic/setuphandlers.py
src/iaweb/mosaic/testing.py
src/iaweb/mosaic/upgrades.py
src/iaweb/mosaic/upgrades.zcml
src/iaweb/mosaic/browser/__init__.py
src/iaweb/mosaic/browser/configure.zcml
src/iaweb/mosaic/browser/overrides/.gitkeep
src/iaweb/mosaic/browser/static/.gitkeep
src/iaweb/mosaic/browser/static/css/iaweb-mosaic-compiled.css
src/iaweb/mosaic/browser/static/css/iaweb-mosaic.css
src/iaweb/mosaic/browser/static/js/iaweb-mosaic-compiled.js
src/iaweb/mosaic/browser/static/js/iaweb-mosaic.js
src/iaweb/mosaic/browser/static/js/jquery.flexslider.js
src/iaweb/mosaic/browser/static/less/iaweb-mosaic-compiled.less.map
src/iaweb/mosaic/browser/static/less/iaweb-mosaic.less
src/iaweb/mosaic/browser/static/less/slider.ideabox.less
src/iaweb/mosaic/locales/README.rst
src/iaweb/mosaic/locales/__init__.py
src/iaweb/mosaic/locales/iaweb.mosaic.pot
src/iaweb/mosaic/locales/update.py
src/iaweb/mosaic/locales/update.sh
src/iaweb/mosaic/locales/en/LC_MESSAGES/iaweb.mosaic.po
src/iaweb/mosaic/locales/fr/LC_MESSAGES/iaweb.mosaic.po
src/iaweb/mosaic/profiles/default/browserlayer.xml
src/iaweb/mosaic/profiles/default/catalog.xml
src/iaweb/mosaic/profiles/default/metadata.xml
src/iaweb/mosaic/profiles/default/registry.xml
src/iaweb/mosaic/profiles/default/rolemap.xml
src/iaweb/mosaic/profiles/uninstall/browserlayer.xml
src/iaweb/mosaic/tests/__init__.py
src/iaweb/mosaic/tests/test_robot.py
src/iaweb/mosaic/tests/test_setup.py
src/iaweb/mosaic/tests/robot/test_example.robot
src/iaweb/mosaic/tile/__init__.py
src/iaweb/mosaic/tile/configure.zcml
src/iaweb/mosaic/tile/slider.py
src/iaweb/mosaic/tile/tiles.py
src/iaweb/mosaic/tile/templates/slider.pt
src/iaweb/mosaic/tile/templates/tile_news.pt